vyper/__init__.py
vyper/__main__.py
vyper/abi_types.py
vyper/exceptions.py
vyper/typing.py
vyper/utils.py
vyper/version.py
vyper/vyper_git_commithash.txt
vyper/warnings.py
vyper/ast/README.md
vyper/ast/__init__.py
vyper/ast/__init__.pyi
vyper/ast/grammar.lark
vyper/ast/grammar.py
vyper/ast/identifiers.py
vyper/ast/metadata.py
vyper/ast/natspec.py
vyper/ast/nodes.py
vyper/ast/nodes.pyi
vyper/ast/parse.py
vyper/ast/pre_parser.py
vyper/ast/utils.py
vyper/ast/validation.py
vyper/builtins/__init__.py
vyper/builtins/_convert.py
vyper/builtins/_signatures.py
vyper/builtins/functions.py
vyper/builtins/interfaces/IERC165.vyi
vyper/builtins/interfaces/IERC20.vyi
vyper/builtins/interfaces/IERC20Detailed.vyi
vyper/builtins/interfaces/IERC4626.vyi
vyper/builtins/interfaces/IERC721.vyi
vyper/builtins/stdlib/math.vy
vyper/cli/__init__.py
vyper/cli/compile_archive.py
vyper/cli/venom_main.py
vyper/cli/vyper_compile.py
vyper/cli/vyper_ir.py
vyper/cli/vyper_json.py
vyper/codegen/__init__.py
vyper/codegen/abi_encoder.py
vyper/codegen/arithmetic.py
vyper/codegen/context.py
vyper/codegen/core.py
vyper/codegen/events.py
vyper/codegen/expr.py
vyper/codegen/external_call.py
vyper/codegen/ir_node.py
vyper/codegen/jumptable_utils.py
vyper/codegen/keccak256_helper.py
vyper/codegen/memory_allocator.py
vyper/codegen/module.py
vyper/codegen/return_.py
vyper/codegen/self_call.py
vyper/codegen/stmt.py
vyper/codegen/function_definitions/__init__.py
vyper/codegen/function_definitions/common.py
vyper/codegen/function_definitions/external_function.py
vyper/codegen/function_definitions/internal_function.py
vyper/compiler/README.md
vyper/compiler/__init__.py
vyper/compiler/input_bundle.py
vyper/compiler/output.py
vyper/compiler/output_bundle.py
vyper/compiler/phases.py
vyper/compiler/settings.py
vyper/compiler/utils.py
vyper/evm/__init__.py
vyper/evm/address_space.py
vyper/evm/opcodes.py
vyper/ir/README.md
vyper/ir/__init__.py
vyper/ir/compile_ir.py
vyper/ir/optimizer.py
vyper/ir/s_expressions.py
vyper-0.4.3.dist-info/LICENSE
vyper-0.4.3.dist-info/METADATA
vyper-0.4.3.dist-info/WHEEL
vyper-0.4.3.dist-info/entry_points.txt
vyper-0.4.3.dist-info/top_level.txt
vyper-0.4.3.dist-info/RECORD
