Metadata-Version: 2.1
Name: vyper
Version: 0.4.3
Summary: Vyper: the Pythonic Programming Language for the EVM
Home-page: https://github.com/vyperlang/vyper
Author: Vyper Team
Author-email: 
License: Apache License 2.0
Keywords: ethereum evm smart contract language
Classifier: Intended Audience :: Developers
Classifier: License :: OSI Approved :: Apache Software License
Classifier: Programming Language :: Python :: 3.10
Classifier: Programming Language :: Python :: 3.11
Classifier: Programming Language :: Python :: 3.12
Classifier: Programming Language :: Python :: 3.13
Requires-Python: >=3.10,<4
Provides-Extra: test
Provides-Extra: lint
Provides-Extra: dev
License-File: LICENSE
